ribasim/__init__.py
ribasim/config.py
ribasim/db_utils.py
ribasim/input_base.py
ribasim/migrations.py
ribasim/model.py
ribasim/py.typed
ribasim/schemas.py
ribasim/styles.py
ribasim/utils.py
ribasim/validation.py
ribasim/delwaq/.gitignore
ribasim/delwaq/README.md
ribasim/delwaq/__init__.py
ribasim/delwaq/generate.py
ribasim/delwaq/parse.py
ribasim/delwaq/plot.py
ribasim/delwaq/util.py
ribasim/delwaq/model/B5_bounddata.inc
ribasim/delwaq/model/bndlist.csv
ribasim/delwaq/model/delwaq-boundary.wrk
ribasim/delwaq/model/delwaq-delwaq03.wrk
ribasim/delwaq/model/delwaq-delwaq04.wrk
ribasim/delwaq/model/delwaq-filenaam.wrk
ribasim/delwaq/model/delwaq-function.wrk
ribasim/delwaq/model/delwaq-harmonic.wrk
ribasim/delwaq/model/delwaq-initials.map
ribasim/delwaq/model/delwaq-output.wrk
ribasim/delwaq/model/delwaq-pointers.wrk
ribasim/delwaq/model/delwaq-proces.wrk
ribasim/delwaq/model/delwaq-timers.out
ribasim/delwaq/model/delwaq-to_from.wrk
ribasim/delwaq/model/delwaq.inp
ribasim/delwaq/model/delwaq.lsp
ribasim/delwaq/model/delwaq.lst
ribasim/delwaq/model/delwaq.map
ribasim/delwaq/model/delwaq.mon
ribasim/delwaq/model/delwaq_map.nc
ribasim/delwaq/model/delwaq_res.map
ribasim/delwaq/model/dimr_config.xml
ribasim/delwaq/model/flows.csv
ribasim/delwaq/model/memory_map.out
ribasim/delwaq/model/network.csv
ribasim/delwaq/model/ribasim.are
ribasim/delwaq/model/ribasim.atr
ribasim/delwaq/model/ribasim.flo
ribasim/delwaq/model/ribasim.len
ribasim/delwaq/model/ribasim.nc
ribasim/delwaq/model/ribasim.poi
ribasim/delwaq/model/ribasim.vel
ribasim/delwaq/model/ribasim.vol
ribasim/delwaq/model/ribasim_bndlist.inc
ribasim/delwaq/model/volumes.csv
ribasim/delwaq/reference/dimr_config.xml
ribasim/delwaq/template/B5_bounddata.inc.j2
ribasim/delwaq/template/delwaq.atr.j2
ribasim/delwaq/template/delwaq.inp.j2
ribasim/geometry/__init__.py
ribasim/geometry/area.py
ribasim/geometry/base.py
ribasim/geometry/link.py
ribasim/geometry/node.py
ribasim/nodes/__init__.py
ribasim/nodes/basin.py
ribasim-2025.5.0.dist-info/METADATA
ribasim-2025.5.0.dist-info/WHEEL
ribasim-2025.5.0.dist-info/licenses/LICENSE
ribasim-2025.5.0.dist-info/RECORD
