Metadata-Version: 2.4
Name: ribasim
Version: 2025.5.0
Summary: Pre- and post-process Ribasim
Project-URL: Documentation, https://ribasim.org/
Project-URL: Source, https://github.com/Deltares/Ribasim
Author-email: Deltares and contributors <ribasim.info@deltares.nl>
License: MIT
License-File: LICENSE
Classifier: Intended Audience :: Science/Research
Classifier: Topic :: Scientific/Engineering :: Hydrology
Requires-Python: >=3.11
Requires-Dist: datacompy>=0.16
Requires-Dist: geopandas>=1.0
Requires-Dist: matplotlib>=3.7
Requires-Dist: netcdf4>=1.7.1
Requires-Dist: numpy>=1.25
Requires-Dist: packaging>=23.0
Requires-Dist: pandas>=2.0
Requires-Dist: pandera>=0.25
Requires-Dist: pyarrow>=17.0
Requires-Dist: pydantic>=2.0
Requires-Dist: pyogrio>=0.8
Requires-Dist: shapely>=2.0
Requires-Dist: tomli-w>=1.0
Requires-Dist: tomli>=2.0
Requires-Dist: xarray>=2025.8.0
Provides-Extra: all
Requires-Dist: jinja2; extra == 'all'
Requires-Dist: networkx; extra == 'all'
Requires-Dist: pytest; extra == 'all'
Requires-Dist: pytest-cov; extra == 'all'
Requires-Dist: pytest-xdist; extra == 'all'
Requires-Dist: ribasim-testmodels; extra == 'all'
Requires-Dist: teamcity-messages; extra == 'all'
Requires-Dist: xugrid; extra == 'all'
Provides-Extra: delwaq
Requires-Dist: jinja2; extra == 'delwaq'
Requires-Dist: networkx; extra == 'delwaq'
Requires-Dist: xugrid; extra == 'delwaq'
Provides-Extra: netcdf
Requires-Dist: xugrid; extra == 'netcdf'
Provides-Extra: tests
Requires-Dist: pytest; extra == 'tests'
Requires-Dist: pytest-cov; extra == 'tests'
Requires-Dist: pytest-xdist; extra == 'tests'
Requires-Dist: ribasim-testmodels; extra == 'tests'
Requires-Dist: teamcity-messages; extra == 'tests'
